[
  {
    "code": "",
    "name": "資產",
    "indent": 0
  },
  {
    "code": "",
    "name": "　流動資產",
    "indent": 1
  },
  {
    "code": "1100",
    "name": "　　現金及約當現金",
    "indent": 2
  },
  {
    "code": "1101",
    "name": "　　　庫存現金",
    "indent": 3
  },
  {
    "code": "1102",
    "name": "　　　零用金∕週轉金",
    "indent": 3
  },
  {
    "code": "1103",
    "name": "　　　銀行存款",
    "indent": 3
  },
  {
    "code": "1105",
    "name": "　　　在途現金",
    "indent": 3
  },
  {
    "code": "1107",
    "name": "　　　約當現金",
    "indent": 3
  },
  {
    "code": "1110",
    "name": "　　透過損益按公允價值衡量之金融資產－流動",
    "indent": 2
  },
  {
    "code": "1111",
    "name": "　　　指定透過損益按公允價值衡量之金融資產－流動",
    "indent": 3
  },
  {
    "code": "1112",
    "name": "　　　指定透過損益按公允價值衡量之金融資產評價調整－流動",
    "indent": 3
  },
  {
    "code": "1113",
    "name": "　　　強制透過損益按公允價值衡量之金融資產－流動",
    "indent": 3
  },
  {
    "code": "1114",
    "name": "　　　強制透過損益按公允價值衡量之金融資產評價調整－流動",
    "indent": 3
  },
  {
    "code": "1120",
    "name": "　　透過其他綜合損益按公允價值衡量之金融資產－流動",
    "indent": 2
  },
  {
    "code": "1121",
    "name": "　　　透過其他綜合損益按公允價值衡量之權益工具投資－流動",
    "indent": 3
  },
  {
    "code": "1122",
    "name": "　　　透過其他綜合損益按公允價值衡量之權益工具投資評價調整－流動",
    "indent": 3
  },
  {
    "code": "1123",
    "name": "　　　透過其他綜合損益按公允價值衡量之債務工具投資－流動",
    "indent": 3
  },
  {
    "code": "1124",
    "name": "　　　透過其他綜合損益按公允價值衡量之債務工具投資評價調整－流動",
    "indent": 3
  },
  {
    "code": "1136",
    "name": "　　按攤銷後成本衡量之金融資產－流動",
    "indent": 2
  },
  {
    "code": "1137",
    "name": "　　　按攤銷後成本衡量之金融資產－流動",
    "indent": 3
  },
  {
    "code": "1138",
    "name": "　　　備抵損失－按攤銷後成本衡量之金融資產－流動",
    "indent": 3
  },
  {
    "code": "1139",
    "name": "　　避險之金融資產－流動",
    "indent": 2
  },
  {
    "code": "1140",
    "name": "　　合約資產－流動",
    "indent": 2
  },
  {
    "code": "1141",
    "name": "　　　合約資產－流動",
    "indent": 3
  },
  {
    "code": "1142",
    "name": "　　　備抵損失－合約資產－流動",
    "indent": 3
  },
  {
    "code": "1150",
    "name": "　　應收票據淨額",
    "indent": 2
  },
  {
    "code": "1151",
    "name": "　　　應收票據",
    "indent": 3
  },
  {
    "code": "1152",
    "name": "　　　其他應收票據",
    "indent": 3
  },
  {
    "code": "1153",
    "name": "　　　應收票據貼現",
    "indent": 3
  },
  {
    "code": "1159",
    "name": "　　　備抵損失－應收票據",
    "indent": 3
  },
  {
    "code": "1160",
    "name": "　　應收票據－關係人淨額",
    "indent": 2
  },
  {
    "code": "1161",
    "name": "　　　應收票據－關係人",
    "indent": 3
  },
  {
    "code": "1162",
    "name": "　　　其他應收票據－關係人",
    "indent": 3
  },
  {
    "code": "1163",
    "name": "　　　應收票據貼現－關係人",
    "indent": 3
  },
  {
    "code": "1169",
    "name": "　　　備抵損失－應收關係人票據",
    "indent": 3
  },
  {
    "code": "1170",
    "name": "　　應收帳款淨額",
    "indent": 2
  },
  {
    "code": "1171",
    "name": "　　　應收銷售及管理費（證券投資信託業適用）",
    "indent": 3
  },
  {
    "code": "1172",
    "name": "　　　應收帳款",
    "indent": 3
  },
  {
    "code": "1173",
    "name": "　　　應收分期帳款",
    "indent": 3
  },
  {
    "code": "1174",
    "name": "　　　未實現利息收入－應收分期帳款",
    "indent": 3
  },
  {
    "code": "1175",
    "name": "　　　應收租賃款",
    "indent": 3
  },
  {
    "code": "1176",
    "name": "　　　融資租賃之未賺得融資收益",
    "indent": 3
  },
  {
    "code": "1177",
    "name": "　　　備抵銷售退回及折讓",
    "indent": 3
  },
  {
    "code": "1178",
    "name": "　　　備抵損失－應收帳款及分期帳款",
    "indent": 3
  },
  {
    "code": "1179",
    "name": "　　　備抵損失－應收帳款、分期帳款及租賃款",
    "indent": 3
  },
  {
    "code": "1180",
    "name": "　　應收帳款－關係人淨額",
    "indent": 2
  },
  {
    "code": "1181",
    "name": "　　　應收帳款－關係人",
    "indent": 3
  },
  {
    "code": "1182",
    "name": "　　　應收分期帳款－關係人",
    "indent": 3
  },
  {
    "code": "1183",
    "name": "　　　未實現利息收入－應收關係人分期帳款",
    "indent": 3
  },
  {
    "code": "1184",
    "name": "　　　應收租賃款－關係人",
    "indent": 3
  },
  {
    "code": "1185",
    "name": "　　　融資租賃之未賺得融資收益－關係人",
    "indent": 3
  },
  {
    "code": "1186",
    "name": "　　　備抵損失－應收帳款及分期帳款－關係人",
    "indent": 3
  },
  {
    "code": "1189",
    "name": "　　　備抵損失－應收關係人帳款、分期帳款及租賃款",
    "indent": 3
  },
  {
    "code": "1190",
    "name": "　　應收建造合約款",
    "indent": 2
  },
  {
    "code": "1195",
    "name": "　　應收建造合約款－關係人",
    "indent": 2
  },
  {
    "code": "1196",
    "name": "　　應收營業租賃款淨額",
    "indent": 2
  },
  {
    "code": "119A",
    "name": "　　　應收營業租賃款",
    "indent": 3
  },
  {
    "code": "119B",
    "name": "　　　備抵損失－應收營業租賃款",
    "indent": 3
  },
  {
    "code": "1197",
    "name": "　　應收融資租賃款淨額",
    "indent": 2
  },
  {
    "code": "119C",
    "name": "　　　應收融資租賃款",
    "indent": 3
  },
  {
    "code": "119D",
    "name": "　　　融資租賃之未賺得融資收益",
    "indent": 3
  },
  {
    "code": "119E",
    "name": "　　　備抵損失－應收融資租賃款",
    "indent": 3
  },
  {
    "code": "1198",
    "name": "　　應收營業租賃款淨額—關係人",
    "indent": 2
  },
  {
    "code": "119F",
    "name": "　　　應收營業租賃款—關係人",
    "indent": 3
  },
  {
    "code": "119G",
    "name": "　　　備抵損失－應收關係人營業租賃款",
    "indent": 3
  },
  {
    "code": "1199",
    "name": "　　應收融資租賃款淨額—關係人",
    "indent": 2
  },
  {
    "code": "119H",
    "name": "　　　應收融資租賃款—關係人",
    "indent": 3
  },
  {
    "code": "119I",
    "name": "　　　融資租賃之未賺得融資收益—關係人",
    "indent": 3
  },
  {
    "code": "119J",
    "name": "　　　備抵損失－應收關係人融資租賃款",
    "indent": 3
  },
  {
    "code": "1200",
    "name": "　　其他應收款",
    "indent": 2
  },
  {
    "code": "1201",
    "name": "　　　應收退稅款",
    "indent": 3
  },
  {
    "code": "1202",
    "name": "　　　未收代收款（海陸運輸業適用）",
    "indent": 3
  },
  {
    "code": "1203",
    "name": "　　　應收工程保留款",
    "indent": 3
  },
  {
    "code": "1204",
    "name": "　　　應收歸墊款",
    "indent": 3
  },
  {
    "code": "1205",
    "name": "　　　應收收益",
    "indent": 3
  },
  {
    "code": "1206",
    "name": "　　　其他應收款－其他",
    "indent": 3
  },
  {
    "code": "1209",
    "name": "　　　備抵損失－其他應收款項",
    "indent": 3
  },
  {
    "code": "1210",
    "name": "　　其他應收款－關係人",
    "indent": 2
  },
  {
    "code": "1211",
    "name": "　　　應收收益－關係人",
    "indent": 3
  },
  {
    "code": "1212",
    "name": "　　　其他應收款－關係人－其他",
    "indent": 3
  },
  {
    "code": "1219",
    "name": "　　　備抵損失－其他應收關係人款項",
    "indent": 3
  },
  {
    "code": "1220",
    "name": "　　本期所得稅資產",
    "indent": 2
  },
  {
    "code": "1221",
    "name": "　　　應收所得稅退稅款",
    "indent": 3
  },
  {
    "code": "1222",
    "name": "　　　預付所得稅",
    "indent": 3
  },
  {
    "code": "130X",
    "name": "　　存貨",
    "indent": 2
  },
  {
    "code": "1300",
    "name": "　　　存貨－買賣業",
    "indent": 3
  },
  {
    "code": "1301",
    "name": "　　　　商品存貨",
    "indent": 4
  },
  {
    "code": "1302",
    "name": "　　　　寄銷品",
    "indent": 4
  },
  {
    "code": "1308",
    "name": "　　　　在途商品",
    "indent": 4
  },
  {
    "code": "1309",
    "name": "　　　　備抵存貨跌價",
    "indent": 4
  },
  {
    "code": "1310",
    "name": "　　　存貨－製造業",
    "indent": 3
  },
  {
    "code": "1311",
    "name": "　　　　製成品",
    "indent": 4
  },
  {
    "code": "1312",
    "name": "　　　　副產品",
    "indent": 4
  },
  {
    "code": "1313",
    "name": "　　　　半成品",
    "indent": 4
  },
  {
    "code": "1314",
    "name": "　　　　在製品",
    "indent": 4
  },
  {
    "code": "1315",
    "name": "　　　　原料",
    "indent": 4
  },
  {
    "code": "1316",
    "name": "　　　　物料",
    "indent": 4
  },
  {
    "code": "1318",
    "name": "　　　　在途原物料",
    "indent": 4
  },
  {
    "code": "1319",
    "name": "　　　　備抵存貨跌價",
    "indent": 4
  },
  {
    "code": "1320",
    "name": "　　　存貨（建設業適用）",
    "indent": 3
  },
  {
    "code": "1321",
    "name": "　　　　待售房地",
    "indent": 4
  },
  {
    "code": "1322",
    "name": "　　　　待售車位",
    "indent": 4
  },
  {
    "code": "1323",
    "name": "　　　　營建用地",
    "indent": 4
  },
  {
    "code": "1324",
    "name": "　　　　在建房地",
    "indent": 4
  },
  {
    "code": "1325",
    "name": "　　　　預付土地款",
    "indent": 4
  },
  {
    "code": "1326",
    "name": "　　　　材料－庫存材料",
    "indent": 4
  },
  {
    "code": "1328",
    "name": "　　　　在途材料",
    "indent": 4
  },
  {
    "code": "1329",
    "name": "　　　　備抵存貨跌價",
    "indent": 4
  },
  {
    "code": "1330",
    "name": "　　　存貨－其他行業",
    "indent": 3
  },
  {
    "code": "1331",
    "name": "　　　　油料",
    "indent": 4
  },
  {
    "code": "1332",
    "name": "　　　　物料",
    "indent": 4
  },
  {
    "code": "1333",
    "name": "　　　　餐飲用品（餐飲業）",
    "indent": 4
  },
  {
    "code": "1338",
    "name": "　　　　其他存貨",
    "indent": 4
  },
  {
    "code": "1339",
    "name": "　　　　備抵存貨跌價",
    "indent": 4
  },
  {
    "code": "1340",
    "name": "　　　農業產品",
    "indent": 3
  },
  {
    "code": "1350",
    "name": "　　　在建工程（營造業適用）",
    "indent": 3
  },
  {
    "code": "1351",
    "name": "　　　　在建材料",
    "indent": 4
  },
  {
    "code": "1352",
    "name": "　　　　在建工料",
    "indent": 4
  },
  {
    "code": "1353",
    "name": "　　　　在建人工",
    "indent": 4
  },
  {
    "code": "1354",
    "name": "　　　　在建費用",
    "indent": 4
  },
  {
    "code": "1355",
    "name": "　　　　待分攤在建費用",
    "indent": 4
  },
  {
    "code": "1356",
    "name": "　　　　在建工程－利息資本化",
    "indent": 4
  },
  {
    "code": "1357",
    "name": "　　　　在建工程－工程損益",
    "indent": 4
  },
  {
    "code": "1400",
    "name": "　　生物資產－流動",
    "indent": 2
  },
  {
    "code": "1401",
    "name": "　　　消耗性生物資產－流動",
    "indent": 3
  },
  {
    "code": "1402",
    "name": "　　　消耗性生物資產－累計折舊－流動",
    "indent": 3
  },
  {
    "code": "1403",
    "name": "　　　消耗性生物資產－累計減損－流動",
    "indent": 3
  },
  {
    "code": "1404",
    "name": "　　　消耗性生物資產公允價值減出售成本累計變動數－流動",
    "indent": 3
  },
  {
    "code": "1405",
    "name": "　　　生產性生物資產－流動",
    "indent": 3
  },
  {
    "code": "1406",
    "name": "　　　生產性生物資產－累計折舊－流動",
    "indent": 3
  },
  {
    "code": "1407",
    "name": "　　　生產性生物資產－累計減損－流動",
    "indent": 3
  },
  {
    "code": "1408",
    "name": "　　　生產性生物資產公允價值減出售成本累計變動數－流動",
    "indent": 3
  },
  {
    "code": "1410",
    "name": "　　預付款項",
    "indent": 2
  },
  {
    "code": "1411",
    "name": "　　　預付薪資",
    "indent": 3
  },
  {
    "code": "1412",
    "name": "　　　預付租金",
    "indent": 3
  },
  {
    "code": "1413",
    "name": "　　　船長週轉金（海陸運輸業適用）",
    "indent": 3
  },
  {
    "code": "1414",
    "name": "　　　預付保險費",
    "indent": 3
  },
  {
    "code": "1415",
    "name": "　　　用品盤存",
    "indent": 3
  },
  {
    "code": "1416",
    "name": "　　　淨確定福利資產-流動",
    "indent": 3
  },
  {
    "code": "1419",
    "name": "　　　其他預付費用",
    "indent": 3
  },
  {
    "code": "1421",
    "name": "　　　預付貨款",
    "indent": 3
  },
  {
    "code": "1422",
    "name": "　　　預付投資款",
    "indent": 3
  },
  {
    "code": "1423",
    "name": "　　　進項稅額",
    "indent": 3
  },
  {
    "code": "1424",
    "name": "　　　留抵稅額",
    "indent": 3
  },
  {
    "code": "1429",
    "name": "　　　其他預付款",
    "indent": 3
  },
  {
    "code": "1450",
    "name": "　　待分配予業主之非流動資產（或處分群組）淨額",
    "indent": 2
  },
  {
    "code": "1451",
    "name": "　　　待分配予業主之非流動資產（或處分群組）",
    "indent": 3
  },
  {
    "code": "1452",
    "name": "　　　累計減損－待分配予業主之非流動資產（或處分群組）",
    "indent": 3
  },
  {
    "code": "1460",
    "name": "　　待出售非流動資產(或處分群組)淨額",
    "indent": 2
  },
  {
    "code": "1461",
    "name": "　　　待出售非流動資產(或處分群組)",
    "indent": 3
  },
  {
    "code": "1462",
    "name": "　　　累計減損-待出售非流動資產(或處分群組)",
    "indent": 3
  },
  {
    "code": "1470",
    "name": "　　其他流動資產",
    "indent": 2
  },
  {
    "code": "1471",
    "name": "　　　暫付款",
    "indent": 3
  },
  {
    "code": "1472",
    "name": "　　　代付款",
    "indent": 3
  },
  {
    "code": "1473",
    "name": "　　　員工（船員）借支",
    "indent": 3
  },
  {
    "code": "1475",
    "name": "　　　代理店往來（海陸運輸業適用）",
    "indent": 3
  },
  {
    "code": "1476",
    "name": "　　　其他金融資產－流動",
    "indent": 3
  },
  {
    "code": "1478",
    "name": "　　　工程存出保證金",
    "indent": 3
  },
  {
    "code": "1479",
    "name": "　　　其他流動資產－其他",
    "indent": 3
  },
  {
    "code": "1480",
    "name": "　　　取得合約之增額成本－流動",
    "indent": 3
  },
  {
    "code": "148A",
    "name": "　　　　取得合約之增額成本－流動",
    "indent": 4
  },
  {
    "code": "148B",
    "name": "　　　　累計減損－取得合約之增額成本－流動",
    "indent": 4
  },
  {
    "code": "1481",
    "name": "　　　待退回產品權利－流動",
    "indent": 3
  },
  {
    "code": "1482",
    "name": "　　　履行合約成本－流動",
    "indent": 3
  },
  {
    "code": "148C",
    "name": "　　　　履行合約成本－流動",
    "indent": 4
  },
  {
    "code": "148D",
    "name": "　　　　累計減損－履行合約成本－流動",
    "indent": 4
  },
  {
    "code": "11XX",
    "name": "　　流動資產合計",
    "indent": 2
  },
  {
    "code": "",
    "name": "　非流動資產",
    "indent": 1
  },
  {
    "code": "1510",
    "name": "　　透過損益按公允價值衡量之金融資產－非流動",
    "indent": 2
  },
  {
    "code": "1511",
    "name": "　　　指定透過損益按公允價值衡量之金融資產－非流動",
    "indent": 3
  },
  {
    "code": "1512",
    "name": "　　　指定透過損益按公允價值衡量之金融資產評價調整－非流動",
    "indent": 3
  },
  {
    "code": "1513",
    "name": "　　　強制透過損益按公允價值衡量之金融資產－非流動",
    "indent": 3
  },
  {
    "code": "1514",
    "name": "　　　強制透過損益按公允價值衡量之金融資產評價調整－非流動",
    "indent": 3
  },
  {
    "code": "1517",
    "name": "　　透過其他綜合損益按公允價值衡量之金融資產－非流動",
    "indent": 2
  },
  {
    "code": "1518",
    "name": "　　　透過其他綜合損益按公允價值衡量之權益工具投資－非流動",
    "indent": 3
  },
  {
    "code": "1519",
    "name": "　　　透過其他綜合損益按公允價值衡量之權益工具投資評價調整－非流動",
    "indent": 3
  },
  {
    "code": "1521",
    "name": "　　　透過其他綜合損益按公允價值衡量之債務工具投資－非流動",
    "indent": 3
  },
  {
    "code": "1522",
    "name": "　　　透過其他綜合損益按公允價值衡量之債務工具投資評價調整－非流動",
    "indent": 3
  },
  {
    "code": "1535",
    "name": "　　按攤銷後成本衡量之金融資產－非流動",
    "indent": 2
  },
  {
    "code": "1536",
    "name": "　　　按攤銷後成本衡量之金融資產－非流動",
    "indent": 3
  },
  {
    "code": "1537",
    "name": "　　　備抵損失－按攤銷後成本衡量之金融資產－非流動",
    "indent": 3
  },
  {
    "code": "1538",
    "name": "　　避險之金融資產－非流動",
    "indent": 2
  },
  {
    "code": "1560",
    "name": "　　合約資產－非流動",
    "indent": 2
  },
  {
    "code": "1561",
    "name": "　　　合約資產－非流動",
    "indent": 3
  },
  {
    "code": "1562",
    "name": "　　　備抵損失－合約資產－非流動",
    "indent": 3
  },
  {
    "code": "1550",
    "name": "　　採用權益法之投資",
    "indent": 2
  },
  {
    "code": "1551",
    "name": "　　　採用權益法之投資",
    "indent": 3
  },
  {
    "code": "1553",
    "name": "　　　累計減損－採用權益法之投資",
    "indent": 3
  },
  {
    "code": "1600",
    "name": "　　不動產、廠房及設備",
    "indent": 2
  },
  {
    "code": "1601",
    "name": "　　　土地淨額",
    "indent": 3
  },
  {
    "code": "1602",
    "name": "　　　　土地成本",
    "indent": 4
  },
  {
    "code": "1603",
    "name": "　　　　土地－重估增（減）值",
    "indent": 4
  },
  {
    "code": "1604",
    "name": "　　　　累計減損－土地",
    "indent": 4
  },
  {
    "code": "1605",
    "name": "　　　土地改良物淨額",
    "indent": 3
  },
  {
    "code": "1606",
    "name": "　　　　土地改良物成本",
    "indent": 4
  },
  {
    "code": "1607",
    "name": "　　　　土地改良物－重估增（減）值",
    "indent": 4
  },
  {
    "code": "1608",
    "name": "　　　　累計折舊－土地改良物",
    "indent": 4
  },
  {
    "code": "1609",
    "name": "　　　　累計減損－土地改良物",
    "indent": 4
  },
  {
    "code": "1610",
    "name": "　　　房屋及建築淨額",
    "indent": 3
  },
  {
    "code": "1611",
    "name": "　　　　房屋及建築成本",
    "indent": 4
  },
  {
    "code": "1612",
    "name": "　　　　房屋及建築－重估增（減）值",
    "indent": 4
  },
  {
    "code": "1613",
    "name": "　　　　累計折舊－房屋及建築",
    "indent": 4
  },
  {
    "code": "1614",
    "name": "　　　　累計減損－房屋及建築",
    "indent": 4
  },
  {
    "code": "1615",
    "name": "　　　機器設備淨額",
    "indent": 3
  },
  {
    "code": "1616",
    "name": "　　　　機器設備成本",
    "indent": 4
  },
  {
    "code": "1617",
    "name": "　　　　機器設備－重估增（減）值",
    "indent": 4
  },
  {
    "code": "1618",
    "name": "　　　　累計折舊－機器設備",
    "indent": 4
  },
  {
    "code": "1619",
    "name": "　　　　累計減損－機器設備",
    "indent": 4
  },
  {
    "code": "1620",
    "name": "　　　裝卸設備淨額",
    "indent": 3
  },
  {
    "code": "1621",
    "name": "　　　　裝卸設備成本",
    "indent": 4
  },
  {
    "code": "1622",
    "name": "　　　　裝卸設備－重估增（減）值",
    "indent": 4
  },
  {
    "code": "1623",
    "name": "　　　　累計折舊－裝卸設備",
    "indent": 4
  },
  {
    "code": "1624",
    "name": "　　　　累計減損－裝卸設備",
    "indent": 4
  },
  {
    "code": "1625",
    "name": "　　　倉儲設備淨額",
    "indent": 3
  },
  {
    "code": "1626",
    "name": "　　　　倉儲設備成本",
    "indent": 4
  },
  {
    "code": "1627",
    "name": "　　　　倉儲設備－重估增（減）值",
    "indent": 4
  },
  {
    "code": "1628",
    "name": "　　　　累計折舊－倉儲設備",
    "indent": 4
  },
  {
    "code": "1629",
    "name": "　　　　累計減損－倉儲設備",
    "indent": 4
  },
  {
    "code": "1630",
    "name": "　　　售氣及輸氣設備淨額",
    "indent": 3
  },
  {
    "code": "1631",
    "name": "　　　　售氣及輸氣設備成本",
    "indent": 4
  },
  {
    "code": "1632",
    "name": "　　　　售氣及輸氣設備－重估增（減）值",
    "indent": 4
  },
  {
    "code": "1633",
    "name": "　　　　累計折舊－售氣及輸氣設備",
    "indent": 4
  },
  {
    "code": "1634",
    "name": "　　　　累計減損－售氣及輸氣設備",
    "indent": 4
  },
  {
    "code": "1635",
    "name": "　　　模具設備淨額",
    "indent": 3
  },
  {
    "code": "1636",
    "name": "　　　　模具設備成本",
    "indent": 4
  },
  {
    "code": "1637",
    "name": "　　　　模具設備－重估增（減）值",
    "indent": 4
  },
  {
    "code": "1638",
    "name": "　　　　累計折舊－模具設備",
    "indent": 4
  },
  {
    "code": "1639",
    "name": "　　　　累計減損－模具設備",
    "indent": 4
  },
  {
    "code": "1640",
    "name": "　　　水電設備淨額",
    "indent": 3
  },
  {
    "code": "1641",
    "name": "　　　　水電設備成本",
    "indent": 4
  },
  {
    "code": "1642",
    "name": "　　　　水電設備－重估增（減）值",
    "indent": 4
  },
  {
    "code": "1643",
    "name": "　　　　累計折舊－水電設備",
    "indent": 4
  },
  {
    "code": "1644",
    "name": "　　　　累計減損－水電設備",
    "indent": 4
  },
  {
    "code": "1645",
    "name": "　　　冷凍設備淨額",
    "indent": 3
  },
  {
    "code": "1646",
    "name": "　　　　冷凍設備成本",
    "indent": 4
  },
  {
    "code": "1647",
    "name": "　　　　冷凍設備－重估增（減）值",
    "indent": 4
  },
  {
    "code": "1648",
    "name": "　　　　累計折舊－冷凍設備",
    "indent": 4
  },
  {
    "code": "1649",
    "name": "　　　　累計減損－冷凍設備",
    "indent": 4
  },
  {
    "code": "1650",
    "name": "　　　漁船設備淨額",
    "indent": 3
  },
  {
    "code": "1651",
    "name": "　　　　漁船設備成本",
    "indent": 4
  },
  {
    "code": "1652",
    "name": "　　　　漁船設備－重估增（減）值",
    "indent": 4
  },
  {
    "code": "1653",
    "name": "　　　　累計折舊－漁船設備",
    "indent": 4
  },
  {
    "code": "1654",
    "name": "　　　　累計減損－漁船設備",
    "indent": 4
  },
  {
    "code": "1655",
    "name": "　　　電腦通訊設備淨額",
    "indent": 3
  },
  {
    "code": "1656",
    "name": "　　　　電腦通訊設備成本",
    "indent": 4
  },
  {
    "code": "1657",
    "name": "　　　　電腦通訊設備－重估增（減）值",
    "indent": 4
  },
  {
    "code": "1658",
    "name": "　　　　累計折舊－電腦通訊設備",
    "indent": 4
  },
  {
    "code": "1659",
    "name": "　　　　累計減損－電腦通訊設備",
    "indent": 4
  },
  {
    "code": "1660",
    "name": "　　　試驗設備淨額",
    "indent": 3
  },
  {
    "code": "1661",
    "name": "　　　　試驗設備成本",
    "indent": 4
  },
  {
    "code": "1662",
    "name": "　　　　試驗設備－重估增（減）值",
    "indent": 4
  },
  {
    "code": "1663",
    "name": "　　　　累計折舊－試驗設備",
    "indent": 4
  },
  {
    "code": "1664",
    "name": "　　　　累計減損－試驗設備",
    "indent": 4
  },
  {
    "code": "1665",
    "name": "　　　污染防治設備淨額",
    "indent": 3
  },
  {
    "code": "1666",
    "name": "　　　　污染防治設備成本",
    "indent": 4
  },
  {
    "code": "1667",
    "name": "　　　　污染防治設備－重估增（減）值",
    "indent": 4
  },
  {
    "code": "1668",
    "name": "　　　　累計折舊－污染防治設備",
    "indent": 4
  },
  {
    "code": "1669",
    "name": "　　　　累計減損－污染防治設備",
    "indent": 4
  },
  {
    "code": "1670",
    "name": "　　　運輸設備淨額",
    "indent": 3
  },
  {
    "code": "1671",
    "name": "　　　　運輸設備成本",
    "indent": 4
  },
  {
    "code": "1672",
    "name": "　　　　運輸設備－重估增（減）值",
    "indent": 4
  },
  {
    "code": "1673",
    "name": "　　　　累計折舊－運輸設備",
    "indent": 4
  },
  {
    "code": "1674",
    "name": "　　　　累計減損－運輸設備",
    "indent": 4
  },
  {
    "code": "1675",
    "name": "　　　船舶設備淨額",
    "indent": 3
  },
  {
    "code": "1676",
    "name": "　　　　船舶設備成本",
    "indent": 4
  },
  {
    "code": "1677",
    "name": "　　　　船舶設備－重估增（減）值",
    "indent": 4
  },
  {
    "code": "1678",
    "name": "　　　　累計折舊－船舶設備",
    "indent": 4
  },
  {
    "code": "1679",
    "name": "　　　　累計減損－船舶設備",
    "indent": 4
  },
  {
    "code": "1680",
    "name": "　　　碼頭設備淨額",
    "indent": 3
  },
  {
    "code": "1681",
    "name": "　　　　碼頭設備成本",
    "indent": 4
  },
  {
    "code": "1682",
    "name": "　　　　碼頭設備－重估增（減）值",
    "indent": 4
  },
  {
    "code": "1683",
    "name": "　　　　累計折舊－碼頭設備",
    "indent": 4
  },
  {
    "code": "1684",
    "name": "　　　　累計減損－碼頭設備",
    "indent": 4
  },
  {
    "code": "1685",
    "name": "　　　飛航設備淨額",
    "indent": 3
  },
  {
    "code": "1686",
    "name": "　　　　飛航設備成本",
    "indent": 4
  },
  {
    "code": "1687",
    "name": "　　　　飛航設備－重估增（減）值",
    "indent": 4
  },
  {
    "code": "1688",
    "name": "　　　　累計折舊－飛航設備",
    "indent": 4
  },
  {
    "code": "1689",
    "name": "　　　　累計減損－飛航設備",
    "indent": 4
  },
  {
    "code": "1690",
    "name": "　　　辦公設備淨額",
    "indent": 3
  },
  {
    "code": "1691",
    "name": "　　　　辦公設備成本",
    "indent": 4
  },
  {
    "code": "1692",
    "name": "　　　　辦公設備－重估增（減）值",
    "indent": 4
  },
  {
    "code": "1693",
    "name": "　　　　累計折舊－辦公設備",
    "indent": 4
  },
  {
    "code": "1694",
    "name": "　　　　累計減損－辦公設備",
    "indent": 4
  },
  {
    "code": "1695",
    "name": "　　　營業器具淨額（觀光飯店業適用）",
    "indent": 3
  },
  {
    "code": "1696",
    "name": "　　　　營業器具成本（觀光飯店業適用）",
    "indent": 4
  },
  {
    "code": "1697",
    "name": "　　　　營業器具－重估增（減）值",
    "indent": 4
  },
  {
    "code": "1698",
    "name": "　　　　累計折舊－營業器具",
    "indent": 4
  },
  {
    "code": "1699",
    "name": "　　　　累計減損－營業器具",
    "indent": 4
  },
  {
    "code": "1700",
    "name": "　　　機具設備淨額",
    "indent": 3
  },
  {
    "code": "1701",
    "name": "　　　　機具設備成本",
    "indent": 4
  },
  {
    "code": "1702",
    "name": "　　　　機具設備－重估增（減）值",
    "indent": 4
  },
  {
    "code": "1703",
    "name": "　　　　累計折舊－機具設備",
    "indent": 4
  },
  {
    "code": "1704",
    "name": "　　　　累計減損－機具設備",
    "indent": 4
  },
  {
    "code": "1705",
    "name": "　　　遊樂設備淨額",
    "indent": 3
  },
  {
    "code": "1706",
    "name": "　　　　遊樂設備成本",
    "indent": 4
  },
  {
    "code": "1707",
    "name": "　　　　遊樂設備－重估增（減）值",
    "indent": 4
  },
  {
    "code": "1708",
    "name": "　　　　累計折舊－遊樂設備",
    "indent": 4
  },
  {
    "code": "1709",
    "name": "　　　　累計減損－遊樂設備",
    "indent": 4
  },
  {
    "code": "1710",
    "name": "　　　景觀園藝淨額",
    "indent": 3
  },
  {
    "code": "1711",
    "name": "　　　　景觀園藝成本",
    "indent": 4
  },
  {
    "code": "1712",
    "name": "　　　　景觀園藝－重估增（減）值",
    "indent": 4
  },
  {
    "code": "1713",
    "name": "　　　　累計折舊－景觀園藝",
    "indent": 4
  },
  {
    "code": "1714",
    "name": "　　　　累計減損－景觀園藝",
    "indent": 4
  },
  {
    "code": "1715",
    "name": "　　　租賃資產淨額",
    "indent": 3
  },
  {
    "code": "1716",
    "name": "　　　　租賃資產成本",
    "indent": 4
  },
  {
    "code": "1717",
    "name": "　　　　租賃資產－重估增（減）值",
    "indent": 4
  },
  {
    "code": "1718",
    "name": "　　　　累計折舊－租賃資產",
    "indent": 4
  },
  {
    "code": "1719",
    "name": "　　　　累計減損－租賃資產",
    "indent": 4
  },
  {
    "code": "1720",
    "name": "　　　出租資產－機器設備淨額",
    "indent": 3
  },
  {
    "code": "1721",
    "name": "　　　　出租資產－機器設備成本",
    "indent": 4
  },
  {
    "code": "1722",
    "name": "　　　　出租資產－機器設備－重估增（減）值",
    "indent": 4
  },
  {
    "code": "1723",
    "name": "　　　　累計折舊－出租資產－機器設備",
    "indent": 4
  },
  {
    "code": "1724",
    "name": "　　　　累計減損－出租資產－機器設備",
    "indent": 4
  },
  {
    "code": "1725",
    "name": "　　　出租資產－其他淨額",
    "indent": 3
  },
  {
    "code": "1726",
    "name": "　　　　出租資產－其他成本",
    "indent": 4
  },
  {
    "code": "1727",
    "name": "　　　　出租資產－其他－重估增（減）值",
    "indent": 4
  },
  {
    "code": "1728",
    "name": "　　　　累計折舊－出租資產－其他",
    "indent": 4
  },
  {
    "code": "1729",
    "name": "　　　　累計減損－出租資產－其他",
    "indent": 4
  },
  {
    "code": "1730",
    "name": "　　　租賃改良淨額",
    "indent": 3
  },
  {
    "code": "1731",
    "name": "　　　　租賃改良成本",
    "indent": 4
  },
  {
    "code": "1732",
    "name": "　　　　租賃改良－重估增（減）值",
    "indent": 4
  },
  {
    "code": "1733",
    "name": "　　　　累計折舊－租賃改良",
    "indent": 4
  },
  {
    "code": "1734",
    "name": "　　　　累計減損－租賃改良",
    "indent": 4
  },
  {
    "code": "1735",
    "name": "　　　其他設備淨額",
    "indent": 3
  },
  {
    "code": "1736",
    "name": "　　　　其他設備成本",
    "indent": 4
  },
  {
    "code": "1737",
    "name": "　　　　其他設備－重估增（減）值",
    "indent": 4
  },
  {
    "code": "1738",
    "name": "　　　　累計折舊－其他設備",
    "indent": 4
  },
  {
    "code": "1739",
    "name": "　　　　累計減損－其他設備",
    "indent": 4
  },
  {
    "code": "1740",
    "name": "　　　未完工程及待驗設備",
    "indent": 3
  },
  {
    "code": "1745",
    "name": "　　　生產性植物",
    "indent": 3
  },
  {
    "code": "1746",
    "name": "　　　　生產性植物成本",
    "indent": 4
  },
  {
    "code": "1747",
    "name": "　　　　生產性植物-累計折舊",
    "indent": 4
  },
  {
    "code": "1748",
    "name": "　　　　生產性植物-累計減損",
    "indent": 4
  },
  {
    "code": "1749",
    "name": "　　　　生產性植物-重估增(減)值",
    "indent": 4
  },
  {
    "code": "1750",
    "name": "　　礦產資源淨額",
    "indent": 2
  },
  {
    "code": "1751",
    "name": "　　　礦產資源成本",
    "indent": 3
  },
  {
    "code": "1752",
    "name": "　　　礦產資源－重估增（減）值",
    "indent": 3
  },
  {
    "code": "1753",
    "name": "　　　累計折耗－礦產資源",
    "indent": 3
  },
  {
    "code": "1754",
    "name": "　　　累計減損－礦產資源",
    "indent": 3
  },
  {
    "code": "1755",
    "name": "　　使用權資產",
    "indent": 2
  },
  {
    "code": "175A",
    "name": "　　　使用權資產－土地淨額",
    "indent": 3
  },
  {
    "code": "17AA",
    "name": "　　　　使用權資產－土地成本",
    "indent": 4
  },
  {
    "code": "17AB",
    "name": "　　　　使用權資產－土地－租賃負債重評估",
    "indent": 4
  },
  {
    "code": "17AC",
    "name": "　　　　使用權資產－土地－重估增(減)值",
    "indent": 4
  },
  {
    "code": "17AD",
    "name": "　　　　累計折舊－使用權資產－土地",
    "indent": 4
  },
  {
    "code": "17AE",
    "name": "　　　　累計減損－使用權資產－土地",
    "indent": 4
  },
  {
    "code": "175B",
    "name": "　　　使用權資產－土地改良物淨額",
    "indent": 3
  },
  {
    "code": "17BA",
    "name": "　　　　使用權資產－土地改良物成本",
    "indent": 4
  },
  {
    "code": "17BB",
    "name": "　　　　使用權資產－土地改良物－租賃負債重評估",
    "indent": 4
  },
  {
    "code": "17BC",
    "name": "　　　　使用權資產－土地改良物－重估增(減)值",
    "indent": 4
  },
  {
    "code": "17BD",
    "name": "　　　　累計折舊－使用權資產－土地改良物",
    "indent": 4
  },
  {
    "code": "17BE",
    "name": "　　　　累計減損－使用權資產－土地改良物",
    "indent": 4
  },
  {
    "code": "175C",
    "name": "　　　使用權資產－房屋及建築淨額",
    "indent": 3
  },
  {
    "code": "17CA",
    "name": "　　　　使用權資產－房屋及建築成本",
    "indent": 4
  },
  {
    "code": "17CB",
    "name": "　　　　使用權資產－房屋及建築－租賃負債重評估",
    "indent": 4
  },
  {
    "code": "17CC",
    "name": "　　　　使用權資產－房屋及建築－重估增(減)值",
    "indent": 4
  },
  {
    "code": "17CD",
    "name": "　　　　累計折舊－使用權資產－房屋及建築",
    "indent": 4
  },
  {
    "code": "17CE",
    "name": "　　　　累計減損－使用權資產－房屋及建築",
    "indent": 4
  },
  {
    "code": "175D",
    "name": "　　　使用權資產－機器設備淨額",
    "indent": 3
  },
  {
    "code": "17DA",
    "name": "　　　　使用權資產－機器設備成本",
    "indent": 4
  },
  {
    "code": "17DB",
    "name": "　　　　使用權資產－機器設備－租賃負債重評估",
    "indent": 4
  },
  {
    "code": "17DC",
    "name": "　　　　使用權資產－機器設備－重估增(減)值",
    "indent": 4
  },
  {
    "code": "17DD",
    "name": "　　　　累計折舊－使用權資產－機器設備",
    "indent": 4
  },
  {
    "code": "17DE",
    "name": "　　　　累計減損－使用權資產－機器設備",
    "indent": 4
  },
  {
    "code": "175E",
    "name": "　　　使用權資產－運輸設備淨額",
    "indent": 3
  },
  {
    "code": "17EA",
    "name": "　　　　使用權資產－運輸設備成本",
    "indent": 4
  },
  {
    "code": "17EB",
    "name": "　　　　使用權資產－運輸設備－租賃負債重評估",
    "indent": 4
  },
  {
    "code": "17EC",
    "name": "　　　　使用權資產－運輸設備－重估增(減)值",
    "indent": 4
  },
  {
    "code": "17ED",
    "name": "　　　　累計折舊－使用權資產－運輸設備",
    "indent": 4
  },
  {
    "code": "17EE",
    "name": "　　　　累計減損－使用權資產－運輸設備",
    "indent": 4
  },
  {
    "code": "175F",
    "name": "　　　使用權資產－辦公設備淨額",
    "indent": 3
  },
  {
    "code": "17FA",
    "name": "　　　　使用權資產－辦公設備成本",
    "indent": 4
  },
  {
    "code": "17FB",
    "name": "　　　　使用權資產－辦公設備－租賃負債重評估",
    "indent": 4
  },
  {
    "code": "17FC",
    "name": "　　　　使用權資產－辦公設備－重估增(減)值",
    "indent": 4
  },
  {
    "code": "17FD",
    "name": "　　　　累計折舊－使用權資產－辦公設備",
    "indent": 4
  },
  {
    "code": "17FE",
    "name": "　　　　累計減損－使用權資產－辦公設備",
    "indent": 4
  },
  {
    "code": "175G",
    "name": "　　　使用權資產－其他資產淨額",
    "indent": 3
  },
  {
    "code": "17GA",
    "name": "　　　　使用權資產－其他資產成本",
    "indent": 4
  },
  {
    "code": "17GB",
    "name": "　　　　使用權資產－其他資產－租賃負債重評估",
    "indent": 4
  },
  {
    "code": "17GC",
    "name": "　　　　使用權資產－其他資產－重估增(減)值",
    "indent": 4
  },
  {
    "code": "17GD",
    "name": "　　　　累計折舊－使用權資產－其他資產",
    "indent": 4
  },
  {
    "code": "17GE",
    "name": "　　　　累計減損－使用權資產－其他資產",
    "indent": 4
  },
  {
    "code": "1760",
    "name": "　　投資性不動產淨額",
    "indent": 2
  },
  {
    "code": "176A",
    "name": "　　　投資性不動產－土地淨額",
    "indent": 3
  },
  {
    "code": "1761",
    "name": "　　　　投資性不動產－土地",
    "indent": 4
  },
  {
    "code": "1762",
    "name": "　　　　投資性不動產－土地－重估增值",
    "indent": 4
  },
  {
    "code": "1763",
    "name": "　　　　投資性不動產－土地－累計公允價值變動數",
    "indent": 4
  },
  {
    "code": "1764",
    "name": "　　　　累計減損－投資性不動產－土地",
    "indent": 4
  },
  {
    "code": "176B",
    "name": "　　　投資性不動產－建築物淨額",
    "indent": 3
  },
  {
    "code": "1765",
    "name": "　　　　投資性不動產－建築物",
    "indent": 4
  },
  {
    "code": "1766",
    "name": "　　　　投資性不動產－建築物－重估增值",
    "indent": 4
  },
  {
    "code": "1767",
    "name": "　　　　投資性不動產－建築物－累計公允價值變動數",
    "indent": 4
  },
  {
    "code": "1768",
    "name": "　　　　累計折舊－投資性不動產－建築物",
    "indent": 4
  },
  {
    "code": "1769",
    "name": "　　　　累計減損－投資性不動產－建築物",
    "indent": 4
  },
  {
    "code": "176C",
    "name": "　　　投資性不動產－租賃權益淨額",
    "indent": 3
  },
  {
    "code": "1771",
    "name": "　　　　投資性不動產－租賃權益",
    "indent": 4
  },
  {
    "code": "1772",
    "name": "　　　　投資性不動產－租賃權益－累計公允價值變動數",
    "indent": 4
  },
  {
    "code": "176D",
    "name": "　　　投資性不動產－使用權資產淨額",
    "indent": 3
  },
  {
    "code": "1776",
    "name": "　　　　投資性不動產－使用權資產",
    "indent": 4
  },
  {
    "code": "1777",
    "name": "　　　　投資性不動產－使用權資產－累計公允價值變動數",
    "indent": 4
  },
  {
    "code": "1778",
    "name": "　　　　累計折舊－投資性不動產－使用權資產",
    "indent": 4
  },
  {
    "code": "1779",
    "name": "　　　　累計減損－投資性不動產－使用權資產",
    "indent": 4
  },
  {
    "code": "176E",
    "name": "　　　建造中之投資性不動產淨額",
    "indent": 3
  },
  {
    "code": "1773",
    "name": "　　　　建造中之投資性不動產",
    "indent": 4
  },
  {
    "code": "1774",
    "name": "　　　　建造中之投資性不動產－累計公允價值變動數",
    "indent": 4
  },
  {
    "code": "1775",
    "name": "　　　　累計減損－建造中之投資性不動產",
    "indent": 4
  },
  {
    "code": "1780",
    "name": "　　無形資產",
    "indent": 2
  },
  {
    "code": "1781",
    "name": "　　　商標權淨額",
    "indent": 3
  },
  {
    "code": "1782",
    "name": "　　　　商標權",
    "indent": 4
  },
  {
    "code": "1783",
    "name": "　　　　商標權重估增（減）值",
    "indent": 4
  },
  {
    "code": "1784",
    "name": "　　　　累計減損－商標權",
    "indent": 4
  },
  {
    "code": "1785",
    "name": "　　　專利權淨額",
    "indent": 3
  },
  {
    "code": "1786",
    "name": "　　　　專利權",
    "indent": 4
  },
  {
    "code": "1787",
    "name": "　　　　專利權重估增（減）值",
    "indent": 4
  },
  {
    "code": "1788",
    "name": "　　　　累計減損－專利權",
    "indent": 4
  },
  {
    "code": "1791",
    "name": "　　　特許權淨額",
    "indent": 3
  },
  {
    "code": "1792",
    "name": "　　　　特許權",
    "indent": 4
  },
  {
    "code": "1793",
    "name": "　　　　特許權重估增（減）值",
    "indent": 4
  },
  {
    "code": "1794",
    "name": "　　　　累計減損－特許權",
    "indent": 4
  },
  {
    "code": "1795",
    "name": "　　　著作權淨額",
    "indent": 3
  },
  {
    "code": "1796",
    "name": "　　　　著作權",
    "indent": 4
  },
  {
    "code": "1797",
    "name": "　　　　著作權重估增（減）值",
    "indent": 4
  },
  {
    "code": "1798",
    "name": "　　　　累計減損－著作權",
    "indent": 4
  },
  {
    "code": "1801",
    "name": "　　　電腦軟體淨額",
    "indent": 3
  },
  {
    "code": "1802",
    "name": "　　　　電腦軟體",
    "indent": 4
  },
  {
    "code": "1803",
    "name": "　　　　電腦軟體重估增（減）值",
    "indent": 4
  },
  {
    "code": "1804",
    "name": "　　　　累計減損－電腦軟體",
    "indent": 4
  },
  {
    "code": "1805",
    "name": "　　　商譽",
    "indent": 3
  },
  {
    "code": "1811",
    "name": "　　　專門技術淨額",
    "indent": 3
  },
  {
    "code": "1812",
    "name": "　　　　專門技術",
    "indent": 4
  },
  {
    "code": "1813",
    "name": "　　　　專門技術重估增（減）值",
    "indent": 4
  },
  {
    "code": "1814",
    "name": "　　　　累計減損－專門技術",
    "indent": 4
  },
  {
    "code": "1821",
    "name": "　　　其他無形資產淨額",
    "indent": 3
  },
  {
    "code": "1822",
    "name": "　　　　其他無形資產",
    "indent": 4
  },
  {
    "code": "1823",
    "name": "　　　　其他無形資產重估增（減）值",
    "indent": 4
  },
  {
    "code": "1824",
    "name": "　　　　累計減損－其他無形資產",
    "indent": 4
  },
  {
    "code": "1825",
    "name": "　　　發展中無形資產淨額",
    "indent": 3
  },
  {
    "code": "1826",
    "name": "　　　　發展中之無形資產",
    "indent": 4
  },
  {
    "code": "1827",
    "name": "　　　　累計減損－發展中之無形資產",
    "indent": 4
  },
  {
    "code": "1830",
    "name": "　　生物資產－非流動",
    "indent": 2
  },
  {
    "code": "1831",
    "name": "　　　消耗性生物資產－非流動",
    "indent": 3
  },
  {
    "code": "1832",
    "name": "　　　消耗性生物資產－累計折舊－非流動",
    "indent": 3
  },
  {
    "code": "1833",
    "name": "　　　消耗性生物資產－累計減損－非流動",
    "indent": 3
  },
  {
    "code": "1834",
    "name": "　　　消耗性生物資產公允價值減出售成本累計變動數－非流動",
    "indent": 3
  },
  {
    "code": "1835",
    "name": "　　　生產性生物資產－非流動",
    "indent": 3
  },
  {
    "code": "1836",
    "name": "　　　生產性生物資產－累計折舊－非流動",
    "indent": 3
  },
  {
    "code": "1837",
    "name": "　　　生產性生物資產－累計減損－非流動",
    "indent": 3
  },
  {
    "code": "1838",
    "name": "　　　生產性生物資產公允價值減出售成本累計變動數－非流動",
    "indent": 3
  },
  {
    "code": "1840",
    "name": "　　遞延所得稅資產",
    "indent": 2
  },
  {
    "code": "1900",
    "name": "　　其他非流動資產",
    "indent": 2
  },
  {
    "code": "1905",
    "name": "　　　有形探勘及評估資產淨額",
    "indent": 3
  },
  {
    "code": "1906",
    "name": "　　　　有形探勘及評估資產成本",
    "indent": 4
  },
  {
    "code": "1907",
    "name": "　　　　有形探勘及評估資產重估增（減）值",
    "indent": 4
  },
  {
    "code": "1908",
    "name": "　　　　累計折舊－有形探勘及評估資產",
    "indent": 4
  },
  {
    "code": "1909",
    "name": "　　　　累計減損－有形探勘及評估資產",
    "indent": 4
  },
  {
    "code": "1910",
    "name": "　　　無形探勘及評估資產淨額",
    "indent": 3
  },
  {
    "code": "1911",
    "name": "　　　　無形探勘及評估資產成本",
    "indent": 4
  },
  {
    "code": "1912",
    "name": "　　　　無形探勘及評估資產重估增（減）值",
    "indent": 4
  },
  {
    "code": "1914",
    "name": "　　　　累計減損－無形探勘及評估資產",
    "indent": 4
  },
  {
    "code": "1915",
    "name": "　　　預付設備款",
    "indent": 3
  },
  {
    "code": "1920",
    "name": "　　　存出保證金",
    "indent": 3
  },
  {
    "code": "1930",
    "name": "　　　長期應收票據及款項",
    "indent": 3
  },
  {
    "code": "1931",
    "name": "　　　　長期應收票據",
    "indent": 4
  },
  {
    "code": "1932",
    "name": "　　　　長期應收款",
    "indent": 4
  },
  {
    "code": "1933",
    "name": "　　　　長期應收分期帳款",
    "indent": 4
  },
  {
    "code": "1934",
    "name": "　　　　未實現利息收入－長期應收分期帳款",
    "indent": 4
  },
  {
    "code": "1935",
    "name": "　　　　長期應收租賃款",
    "indent": 4
  },
  {
    "code": "1936",
    "name": "　　　　融資租賃之未賺得融資收益",
    "indent": 4
  },
  {
    "code": "1937",
    "name": "　　　　催收款項",
    "indent": 4
  },
  {
    "code": "1939",
    "name": "　　　　備抵損失－長期應收款項",
    "indent": 4
  },
  {
    "code": "1940",
    "name": "　　　長期應收票據及款項－關係人",
    "indent": 3
  },
  {
    "code": "1941",
    "name": "　　　　長期應收票據－關係人",
    "indent": 4
  },
  {
    "code": "1942",
    "name": "　　　　長期應收款－關係人",
    "indent": 4
  },
  {
    "code": "1943",
    "name": "　　　　長期應收分期帳款－關係人",
    "indent": 4
  },
  {
    "code": "1944",
    "name": "　　　　未實現利息收入－長期應收關係人分期帳款",
    "indent": 4
  },
  {
    "code": "1945",
    "name": "　　　　長期應收租賃款－關係人",
    "indent": 4
  },
  {
    "code": "1946",
    "name": "　　　　融資租賃之未賺得融資收益－關係人",
    "indent": 4
  },
  {
    "code": "1947",
    "name": "　　　　催收款項－關係人",
    "indent": 4
  },
  {
    "code": "1949",
    "name": "　　　　備抵損失－長期應收關係人款項",
    "indent": 4
  },
  {
    "code": "194A",
    "name": "　　　長期應收營業租賃款淨額",
    "indent": 3
  },
  {
    "code": "194B",
    "name": "　　　　長期應收營業租賃款",
    "indent": 4
  },
  {
    "code": "194C",
    "name": "　　　　備抵損失－長期應收營業租賃款",
    "indent": 4
  },
  {
    "code": "194D",
    "name": "　　　長期應收融資租賃款淨額",
    "indent": 3
  },
  {
    "code": "194E",
    "name": "　　　　長期應收融資租賃款",
    "indent": 4
  },
  {
    "code": "194F",
    "name": "　　　　長期融資租賃之未賺得融資收益",
    "indent": 4
  },
  {
    "code": "194G",
    "name": "　　　　備抵損失－長期應收融資租賃款",
    "indent": 4
  },
  {
    "code": "194H",
    "name": "　　　長期應收營業租賃款淨額—關係人",
    "indent": 3
  },
  {
    "code": "194I",
    "name": "　　　　長期應收營業租賃款—關係人",
    "indent": 4
  },
  {
    "code": "194J",
    "name": "　　　　備抵損失－長期應收關係人營業租賃款",
    "indent": 4
  },
  {
    "code": "194K",
    "name": "　　　長期應收融資租賃款淨額—關係人",
    "indent": 3
  },
  {
    "code": "194L",
    "name": "　　　　長期應收融資租賃款—關係人",
    "indent": 4
  },
  {
    "code": "194M",
    "name": "　　　　長期融資租賃之未賺得融資收益—關係人",
    "indent": 4
  },
  {
    "code": "194N",
    "name": "　　　　備抵損失－長期應收關係人融資租賃款",
    "indent": 4
  },
  {
    "code": "1950",
    "name": "　　　基金",
    "indent": 3
  },
  {
    "code": "1951",
    "name": "　　　　償債基金",
    "indent": 4
  },
  {
    "code": "1952",
    "name": "　　　　改良及擴充基金",
    "indent": 4
  },
  {
    "code": "1953",
    "name": "　　　　其他基金",
    "indent": 4
  },
  {
    "code": "1955",
    "name": "　　　取得合約之增額成本－非流動",
    "indent": 3
  },
  {
    "code": "1956",
    "name": "　　　　取得合約之增額成本－非流動",
    "indent": 4
  },
  {
    "code": "1957",
    "name": "　　　　累計減損－取得合約之增額成本－非流動",
    "indent": 4
  },
  {
    "code": "1960",
    "name": "　　　預付投資款",
    "indent": 3
  },
  {
    "code": "1965",
    "name": "　　　待退回產品權利－非流動",
    "indent": 3
  },
  {
    "code": "1966",
    "name": "　　　履行合約成本－非流動",
    "indent": 3
  },
  {
    "code": "1967",
    "name": "　　　　履行合約成本－非流動",
    "indent": 4
  },
  {
    "code": "1968",
    "name": "　　　　累計減損－履行合約成本－非流動",
    "indent": 4
  },
  {
    "code": "1970",
    "name": "　　　其他長期投資（淨額）",
    "indent": 3
  },
  {
    "code": "1971",
    "name": "　　　　其他長期投資",
    "indent": 4
  },
  {
    "code": "1972",
    "name": "　　　　累計減損－其他長期投資",
    "indent": 4
  },
  {
    "code": "1975",
    "name": "　　　淨確定福利資產-非流動",
    "indent": 3
  },
  {
    "code": "1980",
    "name": "　　　其他金融資產－非流動",
    "indent": 3
  },
  {
    "code": "1981",
    "name": "　　　　人壽保險現金解約價值",
    "indent": 4
  },
  {
    "code": "1984",
    "name": "　　　　其他金融資產－其他－非流動",
    "indent": 4
  },
  {
    "code": "1985",
    "name": "　　　長期預付租金",
    "indent": 3
  },
  {
    "code": "1990",
    "name": "　　　其他非流動資產－其他",
    "indent": 3
  },
  {
    "code": "1992",
    "name": "　　　　未實現售後租回損失",
    "indent": 4
  },
  {
    "code": "1993",
    "name": "　　　　陳飾品",
    "indent": 4
  },
  {
    "code": "1995",
    "name": "　　　　其他非流動資產－其他",
    "indent": 4
  },
  {
    "code": "1996",
    "name": "　　　　內部往來",
    "indent": 4
  },
  {
    "code": "15XX",
    "name": "　　非流動資產合計",
    "indent": 2
  },
  {
    "code": "1XXX",
    "name": "　資產總計",
    "indent": 1
  },
  {
    "code": "",
    "name": "負債及權益",
    "indent": 0
  },
  {
    "code": "",
    "name": "　負債",
    "indent": 1
  },
  {
    "code": "",
    "name": "　　流動負債",
    "indent": 2
  },
  {
    "code": "2100",
    "name": "　　　短期借款",
    "indent": 3
  },
  {
    "code": "2101",
    "name": "　　　　銀行透支",
    "indent": 4
  },
  {
    "code": "2102",
    "name": "　　　　銀行借款",
    "indent": 4
  },
  {
    "code": "2108",
    "name": "　　　　其他短期借款",
    "indent": 4
  },
  {
    "code": "2110",
    "name": "　　　應付短期票券",
    "indent": 3
  },
  {
    "code": "2111",
    "name": "　　　　應付短期票券",
    "indent": 4
  },
  {
    "code": "2116",
    "name": "　　　　附買回債券負債",
    "indent": 4
  },
  {
    "code": "2119",
    "name": "　　　　應付短期票券折價",
    "indent": 4
  },
  {
    "code": "2120",
    "name": "　　　透過損益按公允價值衡量之金融負債－流動",
    "indent": 3
  },
  {
    "code": "2121",
    "name": "　　　　持有供交易金融負債－流動",
    "indent": 4
  },
  {
    "code": "2122",
    "name": "　　　　持有供交易金融負債評價調整－流動",
    "indent": 4
  },
  {
    "code": "2123",
    "name": "　　　　指定為透過損益按公允價值衡量之金融負債－流動",
    "indent": 4
  },
  {
    "code": "2124",
    "name": "　　　　指定為透過損益按公允價值衡量之金融負債評價調整－流動",
    "indent": 4
  },
  {
    "code": "2126",
    "name": "　　　避險之金融負債－流動",
    "indent": 3
  },
  {
    "code": "2128",
    "name": "　　　按攤銷後成本衡量之金融負債－流動",
    "indent": 3
  },
  {
    "code": "2130",
    "name": "　　　合約負債－流動",
    "indent": 3
  },
  {
    "code": "2131",
    "name": "　　　　預收貨款",
    "indent": 4
  },
  {
    "code": "2132",
    "name": "　　　　預收房地款",
    "indent": 4
  },
  {
    "code": "2133",
    "name": "　　　　預收收入",
    "indent": 4
  },
  {
    "code": "2139",
    "name": "　　　　其他合約負債",
    "indent": 4
  },
  {
    "code": "2150",
    "name": "　　　應付票據",
    "indent": 3
  },
  {
    "code": "2151",
    "name": "　　　　應付票據",
    "indent": 4
  },
  {
    "code": "2152",
    "name": "　　　　其他應付票據",
    "indent": 4
  },
  {
    "code": "2160",
    "name": "　　　應付票據－關係人",
    "indent": 3
  },
  {
    "code": "2161",
    "name": "　　　　應付票據－關係人",
    "indent": 4
  },
  {
    "code": "2162",
    "name": "　　　　其他應付票據－關係人",
    "indent": 4
  },
  {
    "code": "2170",
    "name": "　　　應付帳款",
    "indent": 3
  },
  {
    "code": "2171",
    "name": "　　　　應付帳款",
    "indent": 4
  },
  {
    "code": "2172",
    "name": "　　　　暫估應付帳款",
    "indent": 4
  },
  {
    "code": "2180",
    "name": "　　　應付帳款－關係人",
    "indent": 3
  },
  {
    "code": "2181",
    "name": "　　　　應付帳款－關係人",
    "indent": 4
  },
  {
    "code": "2182",
    "name": "　　　　暫估應付帳款－關係人",
    "indent": 4
  },
  {
    "code": "2190",
    "name": "　　　應付建造合約款",
    "indent": 3
  },
  {
    "code": "2195",
    "name": "　　　應付建造合約款－關係人",
    "indent": 3
  },
  {
    "code": "2200",
    "name": "　　　其他應付款",
    "indent": 3
  },
  {
    "code": "2201",
    "name": "　　　　應付薪資",
    "indent": 4
  },
  {
    "code": "2202",
    "name": "　　　　應付租金",
    "indent": 4
  },
  {
    "code": "2203",
    "name": "　　　　應付利息",
    "indent": 4
  },
  {
    "code": "2204",
    "name": "　　　　暫估應付費用",
    "indent": 4
  },
  {
    "code": "2205",
    "name": "　　　　應付退休金費用",
    "indent": 4
  },
  {
    "code": "2206",
    "name": "　　　　應付員工紅利",
    "indent": 4
  },
  {
    "code": "2207",
    "name": "　　　　應付董監事酬勞",
    "indent": 4
  },
  {
    "code": "2209",
    "name": "　　　　其他應付費用",
    "indent": 4
  },
  {
    "code": "2211",
    "name": "　　　　應付工程保留款",
    "indent": 4
  },
  {
    "code": "2212",
    "name": "　　　　應付土地房屋款",
    "indent": 4
  },
  {
    "code": "2213",
    "name": "　　　　應付設備款",
    "indent": 4
  },
  {
    "code": "2214",
    "name": "　　　　銷項稅額",
    "indent": 4
  },
  {
    "code": "2215",
    "name": "　　　　應付營業稅",
    "indent": 4
  },
  {
    "code": "2216",
    "name": "　　　　應付股利",
    "indent": 4
  },
  {
    "code": "2219",
    "name": "　　　　其他應付款－其他",
    "indent": 4
  },
  {
    "code": "2220",
    "name": "　　　其他應付款項－關係人",
    "indent": 3
  },
  {
    "code": "2230",
    "name": "　　　本期所得稅負債",
    "indent": 3
  },
  {
    "code": "2250",
    "name": "　　　負債準備－流動",
    "indent": 3
  },
  {
    "code": "2251",
    "name": "　　　　員工福利負債準備－流動",
    "indent": 4
  },
  {
    "code": "2252",
    "name": "　　　　保固之短期負債準備",
    "indent": 4
  },
  {
    "code": "2253",
    "name": "　　　　重組之短期負債準備",
    "indent": 4
  },
  {
    "code": "2254",
    "name": "　　　　有待法律程序決定之短期負債準備",
    "indent": 4
  },
  {
    "code": "2255",
    "name": "　　　　虧損性合約之短期負債準備",
    "indent": 4
  },
  {
    "code": "2256",
    "name": "　　　　除役、復原及修復成本之短期負債準備",
    "indent": 4
  },
  {
    "code": "2257",
    "name": "　　　　銷貨退回及折讓之短期負債準備",
    "indent": 4
  },
  {
    "code": "2259",
    "name": "　　　　其他短期負債準備",
    "indent": 4
  },
  {
    "code": "2260",
    "name": "　　　與待出售非流動資產直接相關(或處分群組)之負債",
    "indent": 3
  },
  {
    "code": "2265",
    "name": "　　　工程進度請款金額",
    "indent": 3
  },
  {
    "code": "2270",
    "name": "　　　與待分配予業主之非流動資產(或處分群組)直接相關之負債",
    "indent": 3
  },
  {
    "code": "2280",
    "name": "　　　租賃負債－流動",
    "indent": 3
  },
  {
    "code": "2281",
    "name": "　　　　租賃負債－非關係人",
    "indent": 4
  },
  {
    "code": "2282",
    "name": "　　　　租賃負債－關係人",
    "indent": 4
  },
  {
    "code": "2300",
    "name": "　　　其他流動負債",
    "indent": 3
  },
  {
    "code": "2305",
    "name": "　　　　其他金融負債－流動",
    "indent": 4
  },
  {
    "code": "2310",
    "name": "　　　　預收款項",
    "indent": 4
  },
  {
    "code": "2313",
    "name": "　　　　　遞延收入",
    "indent": 5
  },
  {
    "code": "2314",
    "name": "　　　　　預收股本",
    "indent": 5
  },
  {
    "code": "2315",
    "name": "　　　　　其他預收款",
    "indent": 5
  },
  {
    "code": "2320",
    "name": "　　　　一年或一營業週期內到期長期負債",
    "indent": 4
  },
  {
    "code": "2321",
    "name": "　　　　　一年或一營業週期內到期或執行賣回權公司債",
    "indent": 5
  },
  {
    "code": "2322",
    "name": "　　　　　一年或一營業週期內到期長期借款",
    "indent": 5
  },
  {
    "code": "2323",
    "name": "　　　　　一年或一營業週期內到期長期應付票據及款項－非關係人",
    "indent": 5
  },
  {
    "code": "2324",
    "name": "　　　　　一年或一營業週期內到期長期應付票據及款項－關係人",
    "indent": 5
  },
  {
    "code": "2325",
    "name": "　　　　特別股負債－流動",
    "indent": 4
  },
  {
    "code": "2330",
    "name": "　　　　暫收款",
    "indent": 4
  },
  {
    "code": "2335",
    "name": "　　　　代收款",
    "indent": 4
  },
  {
    "code": "2350",
    "name": "　　　　代理店往來（海陸運輸業適用）",
    "indent": 4
  },
  {
    "code": "2355",
    "name": "　　　　應付租賃款－流動",
    "indent": 4
  },
  {
    "code": "2360",
    "name": "　　　　淨確定福利負債-流動",
    "indent": 4
  },
  {
    "code": "2365",
    "name": "　　　　退款負債－流動",
    "indent": 4
  },
  {
    "code": "2370",
    "name": "　　　　財務保證負債－流動",
    "indent": 4
  },
  {
    "code": "2399",
    "name": "　　　　其他流動負債－其他",
    "indent": 4
  },
  {
    "code": "21XX",
    "name": "　　　流動負債合計",
    "indent": 3
  },
  {
    "code": "",
    "name": "　　非流動負債",
    "indent": 2
  },
  {
    "code": "2500",
    "name": "　　　透過損益按公允價值衡量之金融負債－非流動",
    "indent": 3
  },
  {
    "code": "2501",
    "name": "　　　　持有供交易金融負債－非流動",
    "indent": 4
  },
  {
    "code": "2502",
    "name": "　　　　持有供交易金融負債評價調整－非流動",
    "indent": 4
  },
  {
    "code": "2503",
    "name": "　　　　指定為透過損益按公允價值衡量之金融負債－非流動",
    "indent": 4
  },
  {
    "code": "2504",
    "name": "　　　　指定為透過損益按公允價值衡量之金融負債評價調整－非流動",
    "indent": 4
  },
  {
    "code": "2511",
    "name": "　　　避險之金融負債－非流動",
    "indent": 3
  },
  {
    "code": "2520",
    "name": "　　　按攤銷後成本衡量之金融負債－非流動",
    "indent": 3
  },
  {
    "code": "2527",
    "name": "　　　合約負債－非流動",
    "indent": 3
  },
  {
    "code": "2530",
    "name": "　　　應付公司債",
    "indent": 3
  },
  {
    "code": "2531",
    "name": "　　　　應付公司債",
    "indent": 4
  },
  {
    "code": "2532",
    "name": "　　　　應付公司債溢（折）價",
    "indent": 4
  },
  {
    "code": "2540",
    "name": "　　　長期借款",
    "indent": 3
  },
  {
    "code": "2541",
    "name": "　　　　銀行長期借款",
    "indent": 4
  },
  {
    "code": "2542",
    "name": "　　　　其他長期借款",
    "indent": 4
  },
  {
    "code": "2543",
    "name": "　　　　分期償付之借款",
    "indent": 4
  },
  {
    "code": "2550",
    "name": "　　　負債準備－非流動",
    "indent": 3
  },
  {
    "code": "2551",
    "name": "　　　　員工福利負債準備－非流動",
    "indent": 4
  },
  {
    "code": "2552",
    "name": "　　　　保固之長期負債準備",
    "indent": 4
  },
  {
    "code": "2553",
    "name": "　　　　重組之長期負債準備",
    "indent": 4
  },
  {
    "code": "2554",
    "name": "　　　　有待法律程序決定之長期負債準備",
    "indent": 4
  },
  {
    "code": "2555",
    "name": "　　　　虧損性合約之長期負債準備",
    "indent": 4
  },
  {
    "code": "2556",
    "name": "　　　　除役、復原及修復成本之長期負債準備",
    "indent": 4
  },
  {
    "code": "2559",
    "name": "　　　　其他長期負債準備",
    "indent": 4
  },
  {
    "code": "2560",
    "name": "　　　　本期所得稅負債-非流動",
    "indent": 4
  },
  {
    "code": "2570",
    "name": "　　　遞延所得稅負債",
    "indent": 3
  },
  {
    "code": "2571",
    "name": "　　　　遞延所得稅負債－土地增值稅",
    "indent": 4
  },
  {
    "code": "2572",
    "name": "　　　　遞延所得稅負債－所得稅",
    "indent": 4
  },
  {
    "code": "2573",
    "name": "　　　　遞延所得稅負債－其他",
    "indent": 4
  },
  {
    "code": "2580",
    "name": "　　　租賃負債－非流動",
    "indent": 3
  },
  {
    "code": "2581",
    "name": "　　　　租賃負債－非關係人",
    "indent": 4
  },
  {
    "code": "2582",
    "name": "　　　　租賃負債－關係人",
    "indent": 4
  },
  {
    "code": "2600",
    "name": "　　　其他非流動負債",
    "indent": 3
  },
  {
    "code": "2610",
    "name": "　　　　長期應付票據及款項",
    "indent": 4
  },
  {
    "code": "2611",
    "name": "　　　　　長期應付票據",
    "indent": 5
  },
  {
    "code": "2612",
    "name": "　　　　　長期應付款",
    "indent": 5
  },
  {
    "code": "2613",
    "name": "　　　　　應付租賃款－非流動",
    "indent": 5
  },
  {
    "code": "2614",
    "name": "　　　　　長期應付租金",
    "indent": 5
  },
  {
    "code": "2620",
    "name": "　　　　長期應付票據及款項－關係人",
    "indent": 4
  },
  {
    "code": "2621",
    "name": "　　　　　長期應付票據－關係人",
    "indent": 5
  },
  {
    "code": "2622",
    "name": "　　　　　長期應付款－關係人",
    "indent": 5
  },
  {
    "code": "2623",
    "name": "　　　　　長期應付租賃負債－關係人",
    "indent": 5
  },
  {
    "code": "2624",
    "name": "　　　　　長期應付租金－關係人",
    "indent": 5
  },
  {
    "code": "2630",
    "name": "　　　　長期遞延收入",
    "indent": 4
  },
  {
    "code": "2635",
    "name": "　　　　特別股負債－非流動",
    "indent": 4
  },
  {
    "code": "2640",
    "name": "　　　　淨確定福利負債-非流動",
    "indent": 4
  },
  {
    "code": "2645",
    "name": "　　　　存入保證金",
    "indent": 4
  },
  {
    "code": "2650",
    "name": "　　　　採用權益法之投資貸餘",
    "indent": 4
  },
  {
    "code": "2655",
    "name": "　　　　股東往來",
    "indent": 4
  },
  {
    "code": "2665",
    "name": "　　　　未實現售後租回利益",
    "indent": 4
  },
  {
    "code": "2670",
    "name": "　　　　其他非流動負債－其他",
    "indent": 4
  },
  {
    "code": "2675",
    "name": "　　　　退款負債－非流動",
    "indent": 4
  },
  {
    "code": "2680",
    "name": "　　　　財務保證負債－非流動",
    "indent": 4
  },
  {
    "code": "2690",
    "name": "　　　　內部往來",
    "indent": 4
  },
  {
    "code": "25XX",
    "name": "　　　非流動負債合計",
    "indent": 3
  },
  {
    "code": "2XXX",
    "name": "　　負債總計",
    "indent": 2
  },
  {
    "code": "",
    "name": "　權益",
    "indent": 1
  },
  {
    "code": "",
    "name": "　　股本",
    "indent": 2
  },
  {
    "code": "3110",
    "name": "　　　普通股股本",
    "indent": 3
  },
  {
    "code": "3120",
    "name": "　　　特別股股本",
    "indent": 3
  },
  {
    "code": "3130",
    "name": "　　　債券換股權利證書",
    "indent": 3
  },
  {
    "code": "3140",
    "name": "　　　預收股本",
    "indent": 3
  },
  {
    "code": "3150",
    "name": "　　　待分配股票股利",
    "indent": 3
  },
  {
    "code": "3160",
    "name": "　　　特別股轉換普通股權利證書",
    "indent": 3
  },
  {
    "code": "3170",
    "name": "　　　待註銷股本",
    "indent": 3
  },
  {
    "code": "3100",
    "name": "　　　股本合計",
    "indent": 3
  },
  {
    "code": "",
    "name": "　　權益─具證券性質之虛擬通貨",
    "indent": 2
  },
  {
    "code": "3199",
    "name": "　　　權益─具證券性質之虛擬通貨合計",
    "indent": 3
  },
  {
    "code": "",
    "name": "　　資本公積",
    "indent": 2
  },
  {
    "code": "3210",
    "name": "　　　資本公積－發行溢價",
    "indent": 3
  },
  {
    "code": "3211",
    "name": "　　　　資本公積－普通股股票溢價",
    "indent": 4
  },
  {
    "code": "3212",
    "name": "　　　　資本公積－特別股股票溢價",
    "indent": 4
  },
  {
    "code": "3213",
    "name": "　　　　資本公積－轉換公司債轉換溢價",
    "indent": 4
  },
  {
    "code": "3220",
    "name": "　　　資本公積－庫藏股票交易",
    "indent": 3
  },
  {
    "code": "3225",
    "name": "　　　資本公積-買回具證券性質之虛擬通貨",
    "indent": 3
  },
  {
    "code": "3230",
    "name": "　　　資本公積－實際取得或處分子公司股權價格與帳面價值差額",
    "indent": 3
  },
  {
    "code": "3235",
    "name": "　　　資本公積－認列對子公司所有權權益變動數",
    "indent": 3
  },
  {
    "code": "3240",
    "name": "　　　資本公積－處分資產增益",
    "indent": 3
  },
  {
    "code": "3250",
    "name": "　　　資本公積－受贈資產",
    "indent": 3
  },
  {
    "code": "3251",
    "name": "　　　　資本公積－受領股東贈與",
    "indent": 4
  },
  {
    "code": "3252",
    "name": "　　　　資本公積－其他受贈資產",
    "indent": 4
  },
  {
    "code": "3260",
    "name": "　　　資本公積－採用權益法認列關聯企業及合資股權淨值之變動數",
    "indent": 3
  },
  {
    "code": "3265",
    "name": "　　　資本公積－採用權益法認列關聯企業及合資取得或處分子公司股權價格與帳面價值差額",
    "indent": 3
  },
  {
    "code": "3270",
    "name": "　　　資本公積－合併溢額",
    "indent": 3
  },
  {
    "code": "3271",
    "name": "　　　資本公積－員工認股權",
    "indent": 3
  },
  {
    "code": "3272",
    "name": "　　　資本公積－認股權",
    "indent": 3
  },
  {
    "code": "3273",
    "name": "　　　資本公積－限制員工權利股票",
    "indent": 3
  },
  {
    "code": "3280",
    "name": "　　　資本公積－其他",
    "indent": 3
  },
  {
    "code": "3200",
    "name": "　　　資本公積合計",
    "indent": 3
  },
  {
    "code": "",
    "name": "　　保留盈餘",
    "indent": 2
  },
  {
    "code": "3310",
    "name": "　　　法定盈餘公積",
    "indent": 3
  },
  {
    "code": "3320",
    "name": "　　　特別盈餘公積",
    "indent": 3
  },
  {
    "code": "3350",
    "name": "　　　未分配盈餘（或待彌補虧損）",
    "indent": 3
  },
  {
    "code": "3351",
    "name": "　　　　累積盈虧",
    "indent": 4
  },
  {
    "code": "3352",
    "name": "　　　　追溯適用及追溯重編之影響數",
    "indent": 4
  },
  {
    "code": "3353",
    "name": "　　　　本期損益",
    "indent": 4
  },
  {
    "code": "3300",
    "name": "　　　保留盈餘合計",
    "indent": 3
  },
  {
    "code": "",
    "name": "　　其他權益",
    "indent": 2
  },
  {
    "code": "3410",
    "name": "　　　國外營運機構財務報表換算之兌換差額",
    "indent": 3
  },
  {
    "code": "3411",
    "name": "　　　　國外營運機構財務報表換算之兌換差額 －母公司",
    "indent": 4
  },
  {
    "code": "341A",
    "name": "　　　　國外營運機構淨投資避險中屬有效避險部分之避險工具利益(損失)-母公司",
    "indent": 4
  },
  {
    "code": "3412",
    "name": "　　　　國外營運機構財務報表換算之兌換差額－採用權益法之子公司",
    "indent": 4
  },
  {
    "code": "341B",
    "name": "　　　　國外營運機構淨投資避險中屬有效避險部分之避險工具利益(損失)-採用權益法之子公司",
    "indent": 4
  },
  {
    "code": "3413",
    "name": "　　　　國外營運機構財務報表換算之兌換差額－採用權益法之關聯企業及合資",
    "indent": 4
  },
  {
    "code": "341C",
    "name": "　　　　國外營運機構淨投資避險中屬有效避險部分之避險工具利益(損失)-採用權益法之關聯企業及合資",
    "indent": 4
  },
  {
    "code": "3420",
    "name": "　　　透過其他綜合損益按公允價值衡量之金融資產未實現評價損益",
    "indent": 3
  },
  {
    "code": "3421",
    "name": "　　　　透過其他綜合損益按公允價值衡量之權益工具投資未實現評價損益－母公司",
    "indent": 4
  },
  {
    "code": "3422",
    "name": "　　　　透過其他綜合損益按公允價值衡量之權益工具投資未實現評價損益－採用權益法之子公司",
    "indent": 4
  },
  {
    "code": "3423",
    "name": "　　　　透過其他綜合損益按公允價值衡量之權益工具投資未實現評價損益－採用權益法之關聯企業及合資",
    "indent": 4
  },
  {
    "code": "3424",
    "name": "　　　　透過其他綜合損益按公允價值衡量之債務工具投資未實現評價損益－母公司",
    "indent": 4
  },
  {
    "code": "342A",
    "name": "　　　　透過其他綜合損益按公允價值衡量之債務工具投資未實現評價損益－採用權益法之子公司",
    "indent": 4
  },
  {
    "code": "342B",
    "name": "　　　　透過其他綜合損益按公允價值衡量之債務工具投資未實現評價損益－採用權益法之關聯企業及合資",
    "indent": 4
  },
  {
    "code": "342C",
    "name": "　　　　透過其他綜合損益按公允價值衡量之債務工具投資備抵損失－母公司",
    "indent": 4
  },
  {
    "code": "342D",
    "name": "　　　　透過其他綜合損益按公允價值衡量之債務工具投資備抵損失－採用權益法之子公司",
    "indent": 4
  },
  {
    "code": "342E",
    "name": "　　　　透過其他綜合損益按公允價值衡量之債務工具投資備抵損失－採用權益法之關聯企業及合資",
    "indent": 4
  },
  {
    "code": "3440",
    "name": "　　　指定按公允價值衡量之金融負債信用風險變動影響數",
    "indent": 3
  },
  {
    "code": "3441",
    "name": "　　　　指定按公允價值衡量之金融負債信用風險變動影響數-母公司",
    "indent": 4
  },
  {
    "code": "3442",
    "name": "　　　　指定按公允價值衡量之金融負債信用風險變動影響數-採用權益法之子公司",
    "indent": 4
  },
  {
    "code": "3443",
    "name": "　　　　指定按公允價值衡量之金融負債信用風險變動影響數-採用權益法之關聯企業及合資",
    "indent": 4
  },
  {
    "code": "3445",
    "name": "　　　確定福利計畫再衡量數",
    "indent": 3
  },
  {
    "code": "3446",
    "name": "　　　　確定福利計畫再衡量數-母公司",
    "indent": 4
  },
  {
    "code": "3447",
    "name": "　　　　確定福利計畫再衡量數-採用權益法之子公司",
    "indent": 4
  },
  {
    "code": "3448",
    "name": "　　　　確定福利計畫再衡量數-採用權益法之關聯企業及合資",
    "indent": 4
  },
  {
    "code": "3450",
    "name": "　　　避險工具之損益",
    "indent": 3
  },
  {
    "code": "3451",
    "name": "　　　　避險工具之損益－母公司",
    "indent": 4
  },
  {
    "code": "345A",
    "name": "　　　　　現金流量避險中屬有效避險部分之避險工具利益(損失)-母公司",
    "indent": 5
  },
  {
    "code": "345B",
    "name": "　　　　　國外營運機構淨投資避險中屬有效避險部分之避險工具利益(損失)-母公司",
    "indent": 5
  },
  {
    "code": "345C",
    "name": "　　　　　對交易相關之被避險項目進行避險之選擇權時間價值-母公司",
    "indent": 5
  },
  {
    "code": "345D",
    "name": "　　　　　對期間相關之被避險項目進行避險之選擇權時間價值-母公司",
    "indent": 5
  },
  {
    "code": "345E",
    "name": "　　　　　對交易相關之被避險項目進行避險之遠期合約之遠期部分-母公司",
    "indent": 5
  },
  {
    "code": "345F",
    "name": "　　　　　對期間相關之被避險項目進行避險之遠期合約之遠期部分-母公司",
    "indent": 5
  },
  {
    "code": "345G",
    "name": "　　　　　對交易相關之被避險項目進行避險之金融工具之外幣基差-母公司",
    "indent": 5
  },
  {
    "code": "345H",
    "name": "　　　　　對期間相關之被避險項目進行避險之金融工具之外幣基差-母公司",
    "indent": 5
  },
  {
    "code": "3452",
    "name": "　　　　避險工具之損益－採用權益法之子公司",
    "indent": 4
  },
  {
    "code": "345I",
    "name": "　　　　　現金流量避險中屬有效避險部分之避險工具利益(損失)-母公司",
    "indent": 5
  },
  {
    "code": "345J",
    "name": "　　　　　國外營運機構淨投資避險中屬有效避險部分之避險工具利益(損失)-母公司",
    "indent": 5
  },
  {
    "code": "345K",
    "name": "　　　　　對交易相關之被避險項目進行避險之選擇權時間價值-母公司",
    "indent": 5
  },
  {
    "code": "345L",
    "name": "　　　　　對期間相關之被避險項目進行避險之選擇權時間價值-母公司",
    "indent": 5
  },
  {
    "code": "345M",
    "name": "　　　　　對交易相關之被避險項目進行避險之遠期合約之遠期部分-母公司",
    "indent": 5
  },
  {
    "code": "345N",
    "name": "　　　　　對期間相關之被避險項目進行避險之遠期合約之遠期部分-母公司",
    "indent": 5
  },
  {
    "code": "345O",
    "name": "　　　　　對交易相關之被避險項目進行避險之金融工具之外幣基差-母公司",
    "indent": 5
  },
  {
    "code": "345P",
    "name": "　　　　　對期間相關之被避險項目進行避險之金融工具之外幣基差-母公司",
    "indent": 5
  },
  {
    "code": "3453",
    "name": "　　　　避險工具之損益－採用權益法之關聯企業及合資",
    "indent": 4
  },
  {
    "code": "345Q",
    "name": "　　　　　現金流量避險中屬有效避險部分之避險工具利益(損失)-採用權益法之關聯企業及合資)",
    "indent": 5
  },
  {
    "code": "345R",
    "name": "　　　　　國外營運機構淨投資避險中屬有效避險部分之避險工具利益(損失)-採用權益法之關聯企業及合資",
    "indent": 5
  },
  {
    "code": "345S",
    "name": "　　　　　對交易相關之被避險項目進行避險之選擇權時間價值-採用權益法之關聯企業及合資",
    "indent": 5
  },
  {
    "code": "345T",
    "name": "　　　　　對期間相關之被避險項目進行避險之選擇權時間價值-採用權益法之關聯企業及合資",
    "indent": 5
  },
  {
    "code": "345U",
    "name": "　　　　　對交易相關之被避險項目進行避險之遠期合約之遠期部分-採用權益法之關聯企業及合資",
    "indent": 5
  },
  {
    "code": "345V",
    "name": "　　　　　對期間相關之被避險項目進行避險之遠期合約之遠期部分-採用權益法之關聯企業及合資",
    "indent": 5
  },
  {
    "code": "345W",
    "name": "　　　　　對交易相關之被避險項目進行避險之金融工具之外幣基差-採用權益法之關聯企業及合資",
    "indent": 5
  },
  {
    "code": "345X",
    "name": "　　　　　對期間相關之被避險項目進行避險之金融工具之外幣基差-採用權益法之關聯企業及合資",
    "indent": 5
  },
  {
    "code": "3460",
    "name": "　　　不動產重估增值",
    "indent": 3
  },
  {
    "code": "3461",
    "name": "　　　　不動產重估增值－母公司",
    "indent": 4
  },
  {
    "code": "3462",
    "name": "　　　　不動產重估增值－採用權益法之子公司",
    "indent": 4
  },
  {
    "code": "3463",
    "name": "　　　　不動產重估增值－採用權益法之關聯企業及合資",
    "indent": 4
  },
  {
    "code": "3470",
    "name": "　　　與待出售非流動資產(或處分群組)直接相關之權益",
    "indent": 3
  },
  {
    "code": "3471",
    "name": "　　　　與待出售非流動資產(或處分群組)直接相關之權益-母公司",
    "indent": 4
  },
  {
    "code": "3472",
    "name": "　　　　與待出售非流動資產(或處分群組)直接相關之權益-採用權益法之子公司",
    "indent": 4
  },
  {
    "code": "3473",
    "name": "　　　　與待出售非流動資產(或處分群組)直接相關之權益-採用權益法之關聯企業及合資",
    "indent": 4
  },
  {
    "code": "3480",
    "name": "　　　與待分配予業主之非流動資產(或處分群組)直接相關之權益",
    "indent": 3
  },
  {
    "code": "3481",
    "name": "　　　　與待分配予業主之非流動資產(或處分群組)直接相關之權益-母公司",
    "indent": 4
  },
  {
    "code": "3482",
    "name": "　　　　與待分配予業主之非流動資產(或處分群組)直接相關之權益-採用權益法之子公司",
    "indent": 4
  },
  {
    "code": "3483",
    "name": "　　　　與待分配予業主之非流動資產(或處分群組)直接相關之權益-採用權益法之關聯企業及合資",
    "indent": 4
  },
  {
    "code": "3490",
    "name": "　　　其他權益－其他",
    "indent": 3
  },
  {
    "code": "3491",
    "name": "　　　　其他權益－員工未賺得酬勞",
    "indent": 4
  },
  {
    "code": "3499",
    "name": "　　　　其他權益－其他",
    "indent": 4
  },
  {
    "code": "3400",
    "name": "　　　其他權益合計",
    "indent": 3
  },
  {
    "code": "3500",
    "name": "　　庫藏股票",
    "indent": 2
  },
  {
    "code": "35XX",
    "name": "　　共同控制下前手權益",
    "indent": 2
  },
  {
    "code": "355X",
    "name": "　　合併前非屬共同控制股權",
    "indent": 2
  },
  {
    "code": "3XXX",
    "name": "　　權益總計",
    "indent": 2
  },
  {
    "code": "3X2X",
    "name": "　負債及權益總計",
    "indent": 1
  },
  {
    "code": "3997",
    "name": "　待註銷股本股數",
    "indent": 1
  },
  {
    "code": "3998",
    "name": "　預收股款（權益項下）之約當發行股數",
    "indent": 1
  },
  {
    "code": "3999",
    "name": "　母公司暨子公司所持有之母公司庫藏股股數（單位：股）",
    "indent": 1
  }
]